[
    {
        "id":"4",
        "title":"Junior Laravel Developer",
        "period":"October 01, 2023 - Present",
        "company_name":"Lomeyo",
        "company_address":"(5th Floor) 13/A/4/A, Block-B Babar Rd, Dhaka 1207",
        "job_type":"Remote",
        "website":"https://lomeyo.com/"
    },
    {
        "id":"3",
        "title":"Junior Laravel Developer",
        "period":"April 01, 2022 - November 30, 2022",
        "company_name":"CreTechBD",
        "company_address":"House#11/7 (2nd floor) Solimulla Road Mohammadpur, Dhaka",
        "job_type":"Desk",
        "website":"https://cretechbd.com/"
    },
    {
        "id":"2",
        "title":"Intern Laravel Developer",
        "period":"January 01, 2020 - March 30, 2020",
        "company_name":"Winbiz Dizital Ltd",
        "company_address":"House No. 21, Sector-13, Sonargaon Janapath, Uttara, Dhaka -1230",
        "job_type":"Desk",
        "website":"https://winbiz-digital.com/"
    },
    {
        "id":"1",
        "title":"Data Entry Operator",
        "period":"August 21, 2016 - August 17, 2017",
        "company_name":"Asia Projects Engineering Ptd.Ltd",
        "company_address":"32 Penjuru Road, Singapore",
        "job_type":"Desk",
        "website":"https://apeco.com.sg/"
    }




]
